{
  "$schema": "https://fides.community/schemas/organization-catalog/v1",
  "organization": {
    "id": "org:uncefact",
    "name": "UN/CEFACT",
    "sectors": [
      "public_sector"
    ],
    "website": "https://untp.unece.org",
    "country": "CH",
    "description": "Supporting governments and industry on practical measures to counter greenwashing by implementing supply chain traceability and transparency at the scale needed to achieve meaningful impacts on global sustainability outcomes."
  }
}
