{
  "$schema": "https://fides.community/schemas/organization-catalog/v1",
  "organization": {
    "id": "org:medisign",
    "name": "medisign",
    "legalName": "medisign GmbH",
    "sectors": [
      "digital"
    ],
    "country": "DE",
    "certifications": [
      {
        "code": "qtsp",
        "evidence": {
          "kind": "url",
          "url": "https://eidas.ec.europa.eu/efda/trust-services/browse/eidas/tls/tl/DE/tsp/16",
          "label": "EU eIDAS Trust List (Qualified Trust Service Provider)"
        }
      }
    ],
    "website": "http://www.medisign.de/",
    "logo": "https://www.medisign.de/wp-content/uploads/2020/05/medisignPic_eHBA-Signatur_FB.jpg",
    "description": "medisign is listed as a Qualified Trust Service Provider (QTSP) on the EU eIDAS Trust List for Germany, providing digital trust services via medisign.de."
  },
  "lastUpdated": "2026-04-25T06:26:14.660Z"
}
